solfuse/__init__.py
solfuse/custom_detectors/__init__.py
solfuse/custom_detectors/looser_state_machine_detector.py
solfuse/custom_detectors/state_machine_modifiers_detector.py
solfuse/solfuse_ir/__init__.py
solfuse/solfuse_ir/__main__.py
solfuse/solfuse_ir/config.py
solfuse/solfuse_ir/context.py
solfuse/solfuse_ir/debugger.py
solfuse/solfuse_ir/driver.py
solfuse/solfuse_ir/engine.py
solfuse/solfuse_ir/env.py
solfuse/solfuse_ir/expr_handler.py
solfuse/solfuse_ir/function_engine.py
solfuse/solfuse_ir/handler.py
solfuse/solfuse_ir/indent_print.py
solfuse/solfuse_ir/ir_handler.py
solfuse/solfuse_ir/logger.py
solfuse/solfuse_ir/main.py
solfuse/solfuse_ir/naive_node_handler.py
solfuse/solfuse_ir/node_handler.py
solfuse/solfuse_ir/pure_descriptor.py
solfuse/solfuse_ir/scheduler.py
solfuse/solfuse_ir/state_machine.py
solfuse/solfuse_ir/summary.py
solfuse/solfuse_ir/symbol.py
solfuse/solfuse_ir/symbolic_debug.py
solfuse/solfuse_ir/utils.py
solfuse/solfuse_ir/variable_handler.py
solfuse/solfuse_ir/types/__init__.py
solfuse/solfuse_ir/types/elementary.py
solfuse/solfuse_ir/types/type.py
solfuse/solidity_statemachine_gen/__init__.py
solfuse/solidity_statemachine_gen/__main__.py
solfuse/solidity_statemachine_gen/config.py
solfuse/solidity_statemachine_gen/executor.py
solfuse/solidity_statemachine_gen/frame.py
solfuse/solidity_statemachine_gen/function_exec_provider.py
solfuse/solidity_statemachine_gen/indent_print.py
solfuse/solidity_statemachine_gen/logger.py
solfuse/solidity_statemachine_gen/main.py
solfuse/solidity_statemachine_gen/state_machine.py
solfuse/solidity_statemachine_gen/summary.py
solfuse/solidity_statemachine_gen/utils.py
solfuse/solidity_statemachine_gen/variable_type.py
solfuse-1.1.0.dist-info/METADATA
solfuse-1.1.0.dist-info/WHEEL
solfuse-1.1.0.dist-info/entry_points.txt
solfuse-1.1.0.dist-info/licenses/LICENSE
solfuse-1.1.0.dist-info/RECORD
