Metadata-Version: 2.4
Name: SolFuse
Version: 1.1.0
Summary: A Tool to generate state-machine indicating invalid call-chain from Solidity source code.
Project-URL: Homepage, https://gitlab.com/RealDingZhen/solfuse
Author-email: UshioA <shiosshio@outlook.com>
License:                    GNU LESSER GENERAL PUBLIC LICENSE
License-File: LICENSE
Keywords: solidity,state_machine
Classifier: License :: OSI Approved :: GNU Lesser General Public License v3 (LGPLv3)
Classifier: Operating System :: OS Independent
Classifier: Programming Language :: Python :: 3
Requires-Python: >=3.11
Requires-Dist: disjoint-set>=0.8.0
Requires-Dist: pdbp>=1.7.0
Requires-Dist: pygraphviz
Requires-Dist: rich>=14.0.0
Requires-Dist: slither-analyzer
Requires-Dist: solcix>=0.1.8
Requires-Dist: z3-solver
